flask_influxdb2
