Metadata-Version: 1.1
Name: Flask-InfluxDB2
Version: 0.2
Summary: Flask extension for InfluxDB 2.0 client
Home-page: https://github.com/miettal/flask-influxdb2/
Author: Hiromasa Ihara
Author-email: iharahiromasa@gmail.com
License: BSD
Platform: any
Classifier: Environment :: Web Environment
Classifier: Intended Audience :: Developers
Classifier: License :: OSI Approved :: BSD License
Classifier: Operating System :: OS Independent
Classifier: Programming Language :: Python
Classifier: Topic :: Internet :: WWW/HTTP :: Dynamic Content
Classifier: Topic :: Software Development :: Libraries :: Python Modules
